burndown_for_what/views.py
burndown_for_what/admin.py
burndown_for_what/models.py
burndown_for_what/utils.py
burndown_for_what/__init__.py
burndown_for_what/urls.py
burndown_for_what/templates/burndown.html
burndown_for_what/templates/burndown_for_what/base.html
burndown_for_what/migrations/0002_daily_score_unplanned.py
burndown_for_what/migrations/0004_issue.py
burndown_for_what/migrations/0003_auto_20160331_0030.py
burndown_for_what/migrations/__init__.py
burndown_for_what/migrations/0001_initial.py
burndown_for_what/static/js/burndown_for_what.js
burndown_for_what/static/css/burndown_for_what.css
burndown_for_what/templatetags/render_markdown.py
burndown_for_what/templatetags/__init__.py
burndown_for_what/fixtures/initial_data.json
burndown_for_what-0.1.3.dist-info/DESCRIPTION.rst
burndown_for_what-0.1.3.dist-info/WHEEL
burndown_for_what-0.1.3.dist-info/top_level.txt
burndown_for_what-0.1.3.dist-info/METADATA
burndown_for_what-0.1.3.dist-info/RECORD
burndown_for_what-0.1.3.dist-info/metadata.json
