Metadata-Version: 2.0
Name: burndown-for-what
Version: 0.1.3
Summary: Simple django application for generate burndown graphics.
Home-page: https://github.com/guilhermemaba/burndown_for_what
Author: Guilherme Luis Maba
Author-email: guilhermemaba@gmail.com
License: BSD
Keywords: burndown_for_what
Platform: UNKNOWN
Classifier: Development Status :: 3 - Alpha
Classifier: Framework :: Django
Classifier: Intended Audience :: Developers
Classifier: License :: OSI Approved :: BSD License
Classifier: Natural Language :: English
Classifier: Programming Language :: Python :: 2
Classifier: Programming Language :: Python :: 2.7
Classifier: Programming Language :: Python :: 3
Classifier: Programming Language :: Python :: 3.3
Classifier: Programming Language :: Python :: 3.4
